trulens/connectors/snowflake/__init__.py
trulens/connectors/snowflake/connector.py
trulens/connectors/snowflake/dao/enums.py
trulens/connectors/snowflake/dao/external_agent.py
trulens/connectors/snowflake/dao/run.py
trulens/connectors/snowflake/dao/sql_utils.py
trulens/connectors/snowflake/otel_exporter.py
trulens/connectors/snowflake/py.typed
trulens/connectors/snowflake/snowflake_event_table_db.py
trulens/connectors/snowflake/utils/__init__.py
trulens/connectors/snowflake/utils/server_side_evaluation_artifacts.py
trulens/connectors/snowflake/utils/server_side_evaluation_stored_procedure.py
trulens/connectors/snowflake/utils/sis_dashboard_artifacts.py
trulens/data/sis_dashboard/Leaderboard.py
trulens/data/sis_dashboard/environment.yml
trulens/data/sis_dashboard/pages/Compare.py
trulens/data/sis_dashboard/pages/Records.py
trulens/data/snowflake_stage_zips/trulens-connectors-snowflake.zip
trulens/data/snowflake_stage_zips/trulens-core.zip
trulens/data/snowflake_stage_zips/trulens-dashboard.zip
trulens/data/snowflake_stage_zips/trulens-feedback.zip
trulens/data/snowflake_stage_zips/trulens-otel-semconv.zip
trulens/data/snowflake_stage_zips/trulens-providers-cortex.zip
trulens_connectors_snowflake-2.5.3.dist-info/METADATA
trulens_connectors_snowflake-2.5.3.dist-info/WHEEL
trulens_connectors_snowflake-2.5.3.dist-info/RECORD
